citylearn/__init__.py
citylearn/__main__.py
citylearn/base.py
citylearn/building.py
citylearn/citylearn.py
citylearn/cost_function.py
citylearn/data.py
citylearn/dynamics.py
citylearn/electric_vehicle.py
citylearn/electric_vehicle_charger.py
citylearn/energy_model.py
citylearn/occupant.py
citylearn/power_outage.py
citylearn/preprocessing.py
citylearn/reward_function.py
citylearn/rl.py
citylearn/utilities.py
citylearn/wrappers.py
citylearn/agents/__init__.py
citylearn/agents/base.py
citylearn/agents/marlisa.py
citylearn/agents/q_learning.py
citylearn/agents/rbc.py
citylearn/agents/rlc.py
citylearn/agents/sac.py
citylearn/assets/building-0-charge-0.png
citylearn/assets/building-0-charge-1.png
citylearn/assets/building-0-charge-2.png
citylearn/assets/building-0-charge-3.png
citylearn/assets/building-1-charge-0.png
citylearn/assets/building-1-charge-1.png
citylearn/assets/building-1-charge-2.png
citylearn/assets/building-1-charge-3.png
citylearn/assets/glow.png
citylearn/assets/grid.png
citylearn/end_use_load_profiles/__init__.py
citylearn/end_use_load_profiles/clustering.py
citylearn/end_use_load_profiles/neighborhood.py
citylearn/end_use_load_profiles/simulate.py
citylearn/end_use_load_profiles/lstm_model/__init__.py
citylearn/end_use_load_profiles/lstm_model/model.py
citylearn/end_use_load_profiles/lstm_model/model_generation.py
citylearn/end_use_load_profiles/lstm_model/model_generation_wrapper.py
citylearn/end_use_load_profiles/lstm_model/preprocessing.py
citylearn/misc/settings.yaml
citylearn/misc/queries/create_zone_metadata.sql
citylearn/misc/queries/select_citylearn_energy_simulation.sql
citylearn/misc/queries/select_citylearn_weather.sql
citylearn/misc/queries/select_ideal_loads.sql
citylearn/misc/queries/select_lstm_training_data.sql
citylearn/misc/queries/select_zone_conditioning_metadata.sql
citylearn/tests/__init__.py
citylearn/tests/test_battery.py
citylearn/tests/test_electric_vehicle.py
citylearn/tests/test_electric_vehicle_charger.py
CityLearn-2.4.2.dist-info/LICENSE
CityLearn-2.4.2.dist-info/METADATA
CityLearn-2.4.2.dist-info/WHEEL
CityLearn-2.4.2.dist-info/entry_points.txt
CityLearn-2.4.2.dist-info/top_level.txt
CityLearn-2.4.2.dist-info/RECORD
