Metadata-Version: 2.1
Name: CityLearn
Version: 2.4.2
Summary: An open source Farama Foundation Gymnasium environment for benchmarking distributed energy resource control algorithms to provide energy flexibility in a district of buildings.
Home-page: https://github.com/intelligent-environments-lab/CityLearn
Author: Jose Ramon Vazquez-Canteli, Kingsley Nweye, Zoltan Nagy
Author-email: nweye@utexas.edu
Classifier: Programming Language :: Python :: 3
Classifier: License :: OSI Approved :: MIT License
Classifier: Operating System :: OS Independent
Requires-Python: >=3.7.7
License-File: LICENSE
Requires-Dist: doe-xstock>=1.1.0
Requires-Dist: gymnasium
Requires-Dist: nrel-pysam
Requires-Dist: numpy<2.0.0
Requires-Dist: pandas
Requires-Dist: pyyaml
Requires-Dist: scikit-learn<=1.2.2
Requires-Dist: simplejson
Requires-Dist: torch
Requires-Dist: torchvision
Requires-Dist: openstudio<=3.3.0
